yt_quick_insights/__init__.py
yt_quick_insights/cli/__init__.py
yt_quick_insights/cli/cli.py
yt_quick_insights/config.py
yt_quick_insights/data/deep_dive.yml
yt_quick_insights/data/extraction_methods.yml
yt_quick_insights/data/playlist_prompt.yml
yt_quick_insights/data/prompt.yml
yt_quick_insights/frontend/__init__.py
yt_quick_insights/frontend/caching.py
yt_quick_insights/frontend/static/logo.png
yt_quick_insights/frontend/static/styles.css
yt_quick_insights/frontend/streamlit_app.py
yt_quick_insights/frontend/views/__init__.py
yt_quick_insights/frontend/views/components.py
yt_quick_insights/frontend/views/deep_dive.py
yt_quick_insights/frontend/views/env_file.py
yt_quick_insights/frontend/views/extraction_methods.py
yt_quick_insights/frontend/views/playlist_insights.py
yt_quick_insights/frontend/views/video_insights.py
yt_quick_insights/frontend/views/yaml_file.py
yt_quick_insights/quick_insight_helper.py
yt_quick_insights/quick_insights.py
yt_quick_insights/task.py
yt_quick_insights/utils.py
yt_quick_insights/youtube_playlist.py
yt_quick_insights/youtube_transcript.py
yt_quick_insights-1.0.2.dist-info/entry_points.txt
yt_quick_insights-1.0.2.dist-info/LICENSE
yt_quick_insights-1.0.2.dist-info/METADATA
yt_quick_insights-1.0.2.dist-info/WHEEL
yt_quick_insights-1.0.2.dist-info/RECORD
